djangoldp_contact/__init__.py
djangoldp_contact/admin.py
djangoldp_contact/apps.py
djangoldp_contact/check_integrity.py
djangoldp_contact/models.py
djangoldp_contact/settings.py
djangoldp_contact/migrations/0001_initial.py
djangoldp_contact/migrations/0002_auto_20201208_1157.py
djangoldp_contact/migrations/0003_auto_20210218_1145.py
djangoldp_contact/migrations/0004_alter_contact_options_alter_contact_urlid.py
djangoldp_contact/migrations/0005_add_timestamps_to_models.py
djangoldp_contact/migrations/__init__.py
djangoldp_contact/tests/__init__.py
djangoldp_contact/tests/runner.py
djangoldp_contact/tests/tests_permissions.py
djangoldp_contact-5.0.0.dist-info/METADATA
djangoldp_contact-5.0.0.dist-info/WHEEL
djangoldp_contact-5.0.0.dist-info/top_level.txt
djangoldp_contact-5.0.0.dist-info/RECORD
