Metadata-Version: 2.4
Name: djangoldp_contact
Version: 5.0.0
Summary: djangoldp package for circle data models
Home-page: https://git.startinblox.com/djangoldp-packages/djangoldp-contact
Author: Startin'blox
Author-email: jbaptiste@startinblox.com
License: MIT
Requires-Dist: djangoldp~=5.0.0
Requires-Dist: djangoldp_account~=5.0.0
Requires-Dist: djangoldp_notification~=5.0.0
